{"working":false,"featured":false,"private":false,"stars":["5e7a7f587c113618206ddb4f","5e7a7f587c113618206dda13","5e7a7f587c113618206dda9e","5e9f3731658b34001590fe0d","5ebf549b9a2c7b0017693854","5ec10de49a2c7b001769385c","5ec340a7658b34001590feb5","5f0da3e6b1ed0d0014c00003","5f51a9cbb1ed0d0014c0006d","60658fadd4849b0013135d87","615226f5f4fe08001a0a6299","5e7a7f587c113618206ddab4","617581b3f4fe08001a0a62d7","6185ecc5f4fe08001a0a62ee","6187097af4fe08001a0a62ef","61a02c60063978001a1c6f9b","6168c19ff4fe08001a0a62c8","62285666fa14610014830c80","625d52557917e400140a305a","62fba7a8ad0a68001afa5860","63139741d12ead001af40056","631c6ba4d12ead001af46c0d","635835bad12ead001af80602","638230e2d12ead001afa7d6f","63bdfee1d12ead001afe71e4","644d325e454380001a99e411","646f500d454380001a9bce1e","64bbf2515913c5001a3faeee","654f3fa285611d001aef1080","655f3dc085611d001af01f2a","62221c907917e40014067e8c","6612e9d0b9e5d4001a986f73","671aa9599e84f80019d261fa","678e5f332909a9001a02a0d1","679021ca2909a9001a02bd9c","664cf976e0ca9e001a00df42"],"images":[],"categories":["5e7a80dd7c113618206df0ad"],"publicCategories":["Automatically Converted"],"privateCategories":[],"_id":"5e7a7fe77c113618206de6a6","title":"ContinuaVariation","rawFragmentSource":"/*{\n\t\"CREDIT\": \"by mojovideotech\",\n  \"CATEGORIES\" : [\n    \"Automatically Converted\"\n  ],\n  \"INPUTS\" : [\n\n  ],\n  \"DESCRIPTION\" : \"Automatically converted from http:\\/\\/glslsandbox.com\\/e#32770.3\"\n}\n*/\n\n// ContinuaVariation by mojovideotech\n// glslsandbox.com/e#32770.3\n\n// ======================================\n// Corrente Continua - 1k intro (win32)\n// Zerothehero of Topopiccione\n// 25/jul/2012\n//@zerothehero: better formulas, visually improved\n// mod by mojovideotech\n// ======================================\n\n#ifdef GL_ES\nprecision mediump float;\n#endif\n\nconst float di = 0.5772156649;\nconst float dh = 0.69314718;\nconst float twpi = 6.2831853;\n\t\nmat2 rotate2d(float _angle){\n    return mat2(cos(_angle),-sin(_angle),\n                sin(_angle),cos(_angle));\n}\n\nvoid main( void ) \n{\n\tfloat t = TIME*12.;\n\tfloat tt = TIME*0.005;\n\tvec2 p = ((gl_FragCoord.xy / RENDERSIZE.xy )-0.5)*27.;\n\tp.x *= RENDERSIZE.x/RENDERSIZE.y;\n\tfloat a=0.,b=0.,c=0.,d=0.,e=0.;\n\tfor (int i=-4; i<4; i++) {\n\t\tp = rotate2d(tt*-twpi)*p;\n\t\tfloat x = (p.x*di-p.y*dh*0.125);\n\t\tfloat y = (p.x*di*0.125+p.y*dh);\n\t\tc = (sin(x+t*(float(i))/18.0)+b+y+4.0);\n\t\td = (cos(y+t*(float(i))/20.0)+x+a+3.0);\n\t\te = (sin(y+t*(float(i))/17.5)+x-e+1.0);\n\t\ta -= .25/(c*c);\n\t\tb += .5/(d*d);\n\t\te += .125;\n\t}\n\tgl_FragColor = vec4(log(-e+a+b-1.)/8.-0.2,log(-e-a-b-1.)/8.-0.2,log(e-a+b-1.)/5.-0.1, 1.0) ;\n\n}","rawVertexSource":"void main() {\n\tvv_vertShaderInit();\n}","thumbnailCloudinaryId":"l04soxkc8gjuwzl23vfy","description":"Automatically converted from http://glslsandbox.com/e#32770.3","shaderType":"generator","oldId":"1142","createdAt":"2016-05-20T06:31:35.054Z","user":{"_id":"5e7a7f587c113618206dda0d","username":"mojovideotech","name":"Mojo Video Tech","id":"5e7a7f587c113618206dda0d"},"username":"mojovideotech","updatedAt":"2025-04-26T00:50:03.972Z","__v":2,"id":"5e7a7fe77c113618206de6a6"}