{"working":false,"featured":false,"private":false,"stars":["5fd0d59edf59c70014cdc4cf"],"images":[],"categories":["5e7a80dd7c113618206df0a6"],"publicCategories":["Generator"],"privateCategories":[],"_id":"5e7a80477c113618206dee5d","title":"MatrixRain","rawFragmentSource":"/*{\n  \"CREDIT\": \"by mojovideotech\",\n  \"CATEGORIES\" : [\n    \"generator\"\n  ],\n  \"INPUTS\" : [\n  ],\n  \"DESCRIPTION\" : \"based on http:\\/\\/glslsandbox.com\\/e#37192.0\"\n}\n*/\n\n////////////////////////////////////////////////////////////\n// MatrixRain  by mojovideotech\n//\n// based on :  \n// glslsandbox.com/e#37192.0\n//\n// Creative Commons Attribution-NonCommercial-ShareAlike 3.0\n////////////////////////////////////////////////////////////\n\n\nvoid main( void ) \n{\tgl_FragColor = vec4( 0.0, -mod( gl_FragCoord.y + TIME, cos( gl_FragCoord.x*0.75 )+.002 ), 0.0, 1.0 );\n}","rawVertexSource":"void main() {\n\tisf_vertShaderInit();\n}","thumbnailCloudinaryId":"lxt7txknj6f8im7ywox0","description":"based on http://glslsandbox.com/e#37192.0","shaderType":"generator","oldId":"5008","createdAt":"2019-11-15T18:37:51.792Z","user":{"_id":"5e7a7f587c113618206ddd44","username":"sagorgona","name":"Zaniz Alberto Zanella","id":"5e7a7f587c113618206ddd44"},"username":"sagorgona","updatedAt":"2020-12-09T15:33:46.481Z","__v":0,"id":"5e7a80477c113618206dee5d"}