{"working":false,"featured":false,"private":false,"stars":["5e9f3731658b34001590fe0d","5ec340a7658b34001590feb5","5fd4f460df59c70014cdc4da","60513814df59c70014cdc616","6187097af4fe08001a0a62ef","625d52557917e400140a305a","6364f0d524251a001abc94c3","64bbf2515913c5001a3faeee","66823dcdad5cac001983c07b","66cc2e726049470019623d81"],"images":[],"categories":["5e7a80dd7c113618206df0a6"],"publicCategories":["Generator"],"privateCategories":[],"_id":"5e7a7fae7c113618206de279","title":"TunnelV_in_colors","rawFragmentSource":"/*\n{\n  \"CATEGORIES\" : [\"Generator\"\n\n  ],\n  \"DESCRIPTION\" : \"Vortex in colors\",\n  \"INPUTS\" : [\n    \n    {\n      \"NAME\" : \"timeScale\",\n      \"TYPE\" : \"float\",\n      \"MAX\" : 10,\n      \"DEFAULT\" : 0.50,\n      \"MIN\" : 0.1\n    },\n    {\n      \"NAME\" : \"r\",\n      \"TYPE\" : \"float\",\n      \"MAX\" : 1,\n      \"DEFAULT\" : 0.5,\n      \"MIN\" : 0\n    },\n    {\n      \"NAME\" : \"g\",\n      \"TYPE\" : \"float\",\n      \"MAX\" : 1,\n      \"DEFAULT\" : 0.5,\n      \"MIN\" : 0\n    },\n    {\n      \"NAME\" : \"b\",\n      \"TYPE\" : \"float\",\n      \"MAX\" : 1,\n      \"DEFAULT\" : 0.1,\n      \"MIN\" : 0\n    },\n    {\n      \"NAME\" : \"scale\",\n      \"TYPE\" : \"float\",\n      \"MAX\" : 100,\n      \"DEFAULT\" : 0.1,\n      \"MIN\" : 0\n    },\n    \n    {\n      \"NAME\" : \"LIGHT\",\n      \"TYPE\" : \"float\",\n      \"MAX\" : -0.001,\n      \"DEFAULT\" : -0.05,\n      \"MIN\" : -0.15\n    },\n    {\n      \"NAME\" : \"radius\",\n      \"TYPE\" : \"float\",\n      \"MAX\" : 10,\n      \"DEFAULT\" : 1.472574,\n      \"MIN\" : 0.1\n    },\n    {\n      \"NAME\" : \"tilt\",\n      \"TYPE\" : \"float\",\n      \"MAX\" : 1,\n      \"DEFAULT\" :-0.45,\n      \"MIN\" : -1\n    },\n    {\n      \"NAME\" : \"roll\",\n      \"TYPE\" : \"float\",\n      \"MAX\" : 1,\n      \"DEFAULT\" : -0.54,\n      \"MIN\" : -1\n    },\n    {\n      \"NAME\" : \"yaw\",\n      \"TYPE\" : \"float\",\n      \"MAX\" : 1,\n      \"DEFAULT\" : 0.2,\n      \"MIN\" : -1\n    }\n  ],\n  \"ISFVSN\" : \"2\",\n  \"CREDIT\" : \"by thedantheman\"\n}\n*/\n\n#ifdef GL_ES\nprecision mediump float;\n#endif\n\n\n// srtuss, 2014\n// Ported from www.shadertoy.com\n\n#define PI 3.14159265\n\n#define ITER 5\n\nvec2 rotate(vec2 p, float a)\n\t{\n\treturn vec2(p.x * cos(a) - p.y * sin(a), p.x * sin(a) + p.y * cos(a));\n\t}\n\nvec2 circuit(vec2 p)\n\t{\n\tp = fract(p);\n\tfloat r =10.123;\n\tfloat v = 0.0, g = 0.0;\n\tfloat test = 0.0;\n\tr = fract(r * 84.928);\n\tfloat cp, d;\n\t\n\td = p.x;\n\tg += pow(clamp(1.0 - abs(d), 0.0, 1.0), 1000.0);\n\td = p.y;\n\tg += pow(clamp(1.0 - abs(d), 0.0, 1.0), 1000.0);\n\td = p.x - 1.0;\n\tg += pow(clamp(1.0 - abs(d), 0.0, 1.0), 1000.0);\n\td = p.y - 1.0;\n\tg += pow(clamp(1.0 - abs(d), 0.0, 1.0), 10000.0);\n\t\n\tfor(int i = 0; i < ITER; i ++)\n\t\t{\n\t\tcp = 0.5 + (r - 0.5) * 0.9;\n\t\td = p.x - cp;\n\t\tg += pow(clamp(1.0 - abs(d), 0.0, 1.0), 160.0);\n\t\tif(d > 0.0)\n\t\t\t{\n\t\t\tr = fract(r * 4829.013);\n\t\t\tp.x = (p.x - cp) / (1.0 - cp);\n\t\t\tv += 1.0;\n\t\t\ttest = r;\n\t\t\t}\n\t\telse\n\t\t\t{\n\t\t\tr = fract(r * 1239.528);\n\t\t\tp.x = p.x / cp;\n\t\t\ttest = r;\n\t\t\t}\n\t\tp = p.yx;\n\t\t}\n\tv /= float(ITER);\n\treturn vec2(v, g);\n\t}\n\nfloat box(vec2 p, vec2 b, float r)\n\t{\n\treturn length(max(abs(p) - b, 0.0)) -r ;\n\t}\n\nfloat rand(float p)\n\t{\n\treturn fract(sin(p * 591.32) * 43758.5357);\n\t}\n\nfloat rand2(vec2 p)\n\t{\n\treturn fract(sin(dot(p.xy, vec2(12.9898, 78.233))) * 43758.5357);\n\t}\n\nvec2 rand2(float p)\n\t{\n\treturn fract(vec2(sin(p * 591.32), cos(p * 391.32)));\n\t}\n\nvec3 sky(vec3 rd, float t)\n\t{\n\tfloat u = atan(rd.z, rd.x) / PI / abs(sin(radius))*radius;\n\tfloat v = rd.y / length(rd.xz);\n\tfloat fg = exp(LIGHT * abs(v));\n\tvec2 ca = circuit(vec2(u, (v - t * 2.1) * 1.8));\n\t//valeurs lignes précédentes importance de la bande bleu clair\n\tvec2 cb = circuit(vec2(-u, (v - t * 8.1) * 0.1));\n\t//valeurs ligne précédente importance de la bande verte\n\tfloat c = (ca.x - ca.y * 0.5) + cb.y * 0.7;\n\t//effet de bruit lumineux\n\tvec3 glow = pow(vec3(c), vec3(0.2, 3.5, .3) * 2.0);\n\t//en montant les valeurs de la ligne précédente, on augmente l'effet de brillance - contour fluo\n\tvec2 cr = vec2(u, (v - t * 5.0) * 0.03);\n\tfloat crFr = fract(cr.y);\n\tfloat r = smoothstep(0.8, 0.1, abs(crFr * 2.0 - 1.0));\n\tfloat vo = 0.0, gl = 0.0;\n\tfor(int i = 0; i < 6; i ++)\n\t\t{\n\t\tfloat id = float(i);\n\t\tvec2 off = rand2(id);\n\t\tvec2 pp = vec2(fract(cr.x * 5.0 + off.x + t * 8.0 * (0.5 + rand(id))) - 0.5, fract(cr.y * 12.0 + off.y * 0.2) - 0.5);\n\t\tfloat di = box(pp, vec2(0.2, 0.01), 0.02);\n\t\tvo += smoothstep(0.999, 1.0, 1.0 - di);\n\t\tgl += exp(max(di, 0.0) * -16.0);\n\t\t}\n\tvo = pow(vo * 0.4, 2.0);\n\tvec3 qds = vec3(1.0);\n\tvec3 col = mix(glow, qds, clamp(vo, 0.0, 1.0)) + vec3(0.05, 0.05, 0.05) * gl * 0.5;\n\treturn col + (1.0 - fg);\n\t}\n\nvec3 colorset(float v)\n\t{\n\treturn pow(vec3(v),vec3(r, b , g ));\n\t}\n\n\n\nvec3 pixel(vec2 uv)\n\t{\n\tuv /= RENDERSIZE.xy;\n\tuv = uv * 2.0 - 1.0;\n\tuv.x *= RENDERSIZE.x / RENDERSIZE.y;\n\tvec3 ro = vec3(1.0, 1.0, 0.0);\n\tvec3 rd = normalize(vec3(uv, scale));\n\tfloat t = TIME*timeScale;\n\tfloat down = PI / 2.;\n\t//en remplaçant sin par log on change la forme du tunnel, la section à la place d etre circulaire est parabolique\n\trd.yz = rotate(rd.yz, sin(tilt*PI));\n\trd.xz = rotate(rd.xz,  sin(roll)*PI);\n\trd.xy = rotate(rd.xy, sin(yaw)*PI);\n\tvec3 col = sky(rd, t);\n\treturn pow(col, vec3(1.9)) * 1.3;\n\t}\n\n\n\nvoid main()\n\t{\n\tvec2 uv = gl_FragCoord.xy;\n\tvec3 col;\n\tvec2 h = vec2(0.0, 0.0);\n\tcol = pixel(uv);\n\tcol += pixel(uv + h.xy);\n\tcol += pixel(uv + h.yx);\n\tcol += pixel(uv + h.xx);\n\tcol /= 4.0;\n\n\tgl_FragColor = vec4(col, 1.0);\n\tgl_FragColor.b *= b ;\n\tgl_FragColor.g *= g ;\n\tgl_FragColor.r *= r ;\n\t\t\n\t}","rawVertexSource":"void main() {\n\tisf_vertShaderInit();\n}","thumbnailCloudinaryId":"zvcqgvk0cdkq8iimx5sx","description":"Vortex in colors","shaderType":"generator","oldId":"2671","createdAt":"2018-04-29T13:30:04.794Z","user":{"_id":"5e7a7f587c113618206ddb78","username":"sf","name":"Silvia Fabiani","id":"5e7a7f587c113618206ddb78"},"username":"sf","updatedAt":"2024-08-26T08:50:46.300Z","__v":0,"id":"5e7a7fae7c113618206de279"}